README.rst
pyproject.toml
setup.cfg
setup.py
pymugen/__init__.py
pymugen.egg-info/PKG-INFO
pymugen.egg-info/SOURCES.txt
pymugen.egg-info/dependency_links.txt
pymugen.egg-info/requires.txt
pymugen.egg-info/top_level.txt
pymugen/fasta/__init__.py
pymugen/fasta/chromosome.py
pymugen/fasta/fastaReader.py
pymugen/fasta/sequence.py
pymugen/transformers/__init__.py
pymugen/transformers/extendedTransformer.py
pymugen/transformers/mutationTransformer.py
pymugen/transformers/transformer.py
pymugen/utils/__init__.py
pymugen/utils/genomics.py
tests/__init__.py
tests/test_chromosome.py
tests/test_extended_parser_vcf.py
tests/test_fasta_reader.py
tests/test_genomics.py
tests/test_mutation_parser.py
tests/test_pymut.py
tests/test_sequence.py