Metadata-Version: 2.1
Name: pymugen
Version: 1.2.1
Summary: Management about FASTA and VCF files.
Home-page: https://github.com/agranadosb/pymugen
Author: Alejandro Granados
Author-email: agranadosb55199@outlook.com
License: MIT
Download-URL: https://github.com/agranadosb/pymugen/archive/refs/heads/main.zip
Keywords: VCF,FASTA,Genomics
Platform: UNKNOWN
Classifier: Development Status :: 3 - Alpha
Classifier: Intended Audience :: Developers
Classifier: Topic :: Software Development :: Build Tools
Classifier: License :: OSI Approved :: MIT License
Classifier: Programming Language :: Python :: 3.8
